opensarlab_theme_light/__init__.py
opensarlab_theme_light/_version.py
opensarlab_theme_light/labextension/package.json
opensarlab_theme_light/labextension/static/568.fa54804b31f7ce72590d.js
opensarlab_theme_light/labextension/static/remoteEntry.d8dc81635b4871b80f39.js
opensarlab_theme_light/labextension/static/style.js
opensarlab_theme_light/labextension/static/third-party-licenses.json
opensarlab_theme_light/labextension/themes/opensarlab-theme-light/index.css
opensarlab_theme_light/labextension/themes/opensarlab-theme-light/index.js
opensarlab_theme_light-0.1.1.data/data/share/jupyter/labextensions/opensarlab-theme-light/install.json
opensarlab_theme_light-0.1.1.data/data/share/jupyter/labextensions/opensarlab-theme-light/package.json
opensarlab_theme_light-0.1.1.data/data/share/jupyter/labextensions/opensarlab-theme-light/static/568.fa54804b31f7ce72590d.js
opensarlab_theme_light-0.1.1.data/data/share/jupyter/labextensions/opensarlab-theme-light/static/remoteEntry.d8dc81635b4871b80f39.js
opensarlab_theme_light-0.1.1.data/data/share/jupyter/labextensions/opensarlab-theme-light/static/style.js
opensarlab_theme_light-0.1.1.data/data/share/jupyter/labextensions/opensarlab-theme-light/static/third-party-licenses.json
opensarlab_theme_light-0.1.1.data/data/share/jupyter/labextensions/opensarlab-theme-light/themes/opensarlab-theme-light/index.css
opensarlab_theme_light-0.1.1.data/data/share/jupyter/labextensions/opensarlab-theme-light/themes/opensarlab-theme-light/index.js
opensarlab_theme_light-0.1.1.dist-info/LICENSE
opensarlab_theme_light-0.1.1.dist-info/METADATA
opensarlab_theme_light-0.1.1.dist-info/WHEEL
opensarlab_theme_light-0.1.1.dist-info/top_level.txt
opensarlab_theme_light-0.1.1.dist-info/RECORD
